sql_server/__init__.py
sql_server/pyodbc/__init__.py
sql_server/pyodbc/base.py
sql_server/pyodbc/client.py
sql_server/pyodbc/compiler.py
sql_server/pyodbc/creation.py
sql_server/pyodbc/features.py
sql_server/pyodbc/introspection.py
sql_server/pyodbc/operations.py
sql_server/pyodbc/schema.py
django_pyodbc_azure_2019-2.1.0.0.dist-info/LICENSE
django_pyodbc_azure_2019-2.1.0.0.dist-info/METADATA
django_pyodbc_azure_2019-2.1.0.0.dist-info/WHEEL
django_pyodbc_azure_2019-2.1.0.0.dist-info/top_level.txt
django_pyodbc_azure_2019-2.1.0.0.dist-info/RECORD
