Metadata-Version: 1.1
Name: django-pyodbc-azure-2019
Version: 2.1.0.0
Summary: Django backend for Microsoft SQL Server and Azure SQL Database using pyodbc, compatible with SQL Server 2019
Home-page: https://github.com/escuccim/django-pyodbc-azure
Author: Michiya Takahashi, updated by Eric A Scuccimarra (skooch@gmail.com)
Author-email: michiya.takahashi@gmail.com
License: BSD
Keywords: azure django
Platform: UNKNOWN
Classifier: Development Status :: 4 - Beta
Classifier: License :: OSI Approved :: BSD License
Classifier: Framework :: Django
Classifier: Programming Language :: Python
Classifier: Programming Language :: Python :: 3
Classifier: Programming Language :: Python :: 3.5
Classifier: Programming Language :: Python :: 3.6
Classifier: Programming Language :: Python :: 3.7
Classifier: Topic :: Internet :: WWW/HTTP
